streamlit_svg_view/__init__.py
streamlit_svg_view/frontend/public/index.html
streamlit_svg_view-0.2.0.dist-info/METADATA
streamlit_svg_view-0.2.0.dist-info/WHEEL
streamlit_svg_view-0.2.0.dist-info/licenses/LICENSE
streamlit_svg_view-0.2.0.dist-info/RECORD
