Metadata-Version: 2.4
Name: streamlit-svg-view
Version: 0.2.0
Summary: A Streamlit custom component for displaying SVG animations with interactive play, pause, and restart controls
Project-URL: Homepage, https://github.com/kazuar/streamlit-svg-view
Project-URL: Repository, https://github.com/kazuar/streamlit-svg-view
Project-URL: Issues, https://github.com/kazuar/streamlit-svg-view/issues
Project-URL: Documentation, https://github.com/kazuar/streamlit-svg-view/blob/main/README.md
Author-email: Isaac Vidas <isaac@vid.as>
License: MIT
License-File: LICENSE
Keywords: animation,component,interactive,streamlit,svg
Classifier: Development Status :: 4 - Beta
Classifier: Intended Audience :: Developers
Classifier: License :: OSI Approved :: MIT License
Classifier: Operating System :: OS Independent
Classifier: Programming Language :: Python :: 3
Classifier: Programming Language :: Python :: 3.9
Classifier: Programming Language :: Python :: 3.10
Classifier: Programming Language :: Python :: 3.11
Classifier: Programming Language :: Python :: 3.12
Classifier: Topic :: Scientific/Engineering :: Visualization
Classifier: Topic :: Software Development :: User Interfaces
Requires-Python: >=3.9
Requires-Dist: streamlit>=1.0.0
Provides-Extra: dev
Requires-Dist: black; extra == 'dev'
Requires-Dist: isort; extra == 'dev'
Requires-Dist: mypy; extra == 'dev'
Requires-Dist: pytest; extra == 'dev'
